Workbook

Sheet Home
A1: BANK — ANALYTICS DASHBOARD | N1: ▼ FILTERS
N3: Filter by Branch:
A4: Banking & Loan Analytics | Group B | 5-Module Overview | N4: All Branches
B6: =Calc!B3 -> 400 | E6: =TEXT(Calc!B4,"#,##0") -> 359,793,000 | H6: =Calc!B5 -> 3606 | K6: =TEXT(Calc!B6,"0.0")&"%" -> 93.7%
B8: TOTAL CUSTOMERS | E8: TOTAL LOAN BOOK (₹) | H8: TOTAL TRANSACTIONS | K8: AVG REPAYMENT RATE
B10: Explore the 5 Modules
B11: 1. Customer Analytics | E11: 2. Transaction Analytics | H11: 3. Loan Portfolio | K11: 4. EMI & Repayment
B13: Demographics, income & account profile | E13: Volume, value & activity trends | H13: Loan book by type, amount & status | K13: Repayment rate & overdue tracking
B15: =HYPERLINK("#'Customer'!A1","View Module →") -> View Module → | E15: =HYPERLINK("#'Transaction'!A1","View Module →") -> View Module → | H15: =HYPERLINK("#'LoanPortfolio'!A1","View Module →") -> View Module → | K15: =HYPERLINK("#'EMI_Repayment'!A1","View Module →") -> View Module →
B17: 5. Branch Performance
B19: Branch-wise comparison & ranking
B21: =HYPERLINK("#'BranchPerf'!A1","View Module →") -> View Module →

Sheet Customer
A1: MODULE 1 — CUSTOMER ANALYTICS | N1: ▼ FILTERS
N3: Filter by Branch:
A4: Who are our customers: demographics, income & account profile | N4: Agra Sadar Branch
B6: =Calc!B31 -> 77 | E6: =TEXT(Calc!B32,"0.0")&" yrs" -> 36.4 yrs | H6: =TEXT(Calc!B33,"#,##0") -> 50,632 | K6: 5 Branches Across North India
B8: TOTAL CUSTOMERS | E8: AVERAGE AGE | H8: AVG MONTHLY INCOME (₹)
N9: Data source: RawData_Customers sheet (CustTbl), 400 rows. This filter narrows every KPI and chart on this page to the chosen branch.
B10: Customer Profile Charts
N13: =HYPERLINK("#Home!A1","← Back to Home") -> ← Back to Home

Sheet Transaction
A1: MODULE 2 — TRANSACTION ANALYTICS | N1: ▼ FILTERS
N3: Filter by Branch:
A4: Transaction volume, value & activity trends over the last 12 months | N4: Kanpur Civil Lines Branch
B6: =Calc!B76 -> 605 | E6: =TEXT(Calc!B77,"#,##0") -> 11,670,458 | H6: =TEXT(Calc!B78,"#,##0") -> 19,290 | K6: 12-Month Activity Window
B8: TOTAL TRANSACTIONS | E8: TOTAL VALUE (₹) | H8: AVG TRANSACTION VALUE (₹)
N9: Data source: RawData_Transactions sheet (TxnTbl), 3,606 rows covering Sep 2025 to Aug 2026.
B10: Transaction Pattern Charts
N13: =HYPERLINK("#Home!A1","← Back to Home") -> ← Back to Home

Sheet LoanPortfolio
A1: MODULE 3 — LOAN PORTFOLIO | N1: ▼ FILTERS
N3: Filter by Branch:
A4: Loan book composition by type, amount, interest rate & status | N4: All Branches
B6: =Calc!B136 -> 320 | E6: =TEXT(Calc!B137,"#,##0") -> 359,793,000 | H6: =TEXT(Calc!B138,"#,##0") -> 1,124,353 | K6: =TEXT(Calc!B139,"0.00")&"%" -> 11.25%
B8: TOTAL LOANS | E8: TOTAL LOAN AMOUNT (₹) | H8: AVG LOAN AMOUNT (₹) | K8: AVG INTEREST RATE
N9: Data source: RawData_Loans sheet (LoanTbl), 320 loans across 4 loan types: Home, Personal, Auto, Business.
B10: Loan Book Charts
N13: =HYPERLINK("#Home!A1","← Back to Home") -> ← Back to Home

Sheet EMI_Repayment
A1: MODULE 4 — EMI & REPAYMENT ANALYSIS | N1: ▼ FILTERS
N3: Filter by Branch:
A4: EMI amounts, repayment consistency & overdue tracking | N4: Meerut Cantt Branch
B6: =TEXT(Calc!B159,"0.0")&"%" -> 94.0% | E6: =Calc!B160 -> 18 | H6: =TEXT(Calc!B161,"#,##0") -> 52,291,274 | K6: =TEXT(Calc!B162,"0.0")&"%" -> 12.9%
B8: AVG REPAYMENT RATE | E8: LOANS OVERDUE (3+ missed) | H8: EST. EMI COLLECTED (₹) | K8: ON-TIME LOANS (0 missed)
N9: Data source: RawData_Loans sheet — EMIsPaid / EMIsMissed / MonthsElapsed columns, aggregated per loan type.
B10: Repayment Behaviour Charts
N13: =HYPERLINK("#Home!A1","← Back to Home") -> ← Back to Home

Sheet BranchPerf
A1: MODULE 5 — BRANCH PERFORMANCE | N1: ▼ FILTERS
N3: Highlight Branch:
A4: Comparing all 5 branches on customers, loans, transactions & repayment | N4: Agra Sadar Branch
B6: =Calc!B199 -> 77 | E6: =TEXT(Calc!B200,"#,##0") -> 63,121,000 | H6: =TEXT(Calc!B201,"#,##0") -> 12,531,235 | K6: =TEXT(Calc!B202,"0.0")&"%" -> 93.3%
B8: SELECTED: CUSTOMERS | E8: SELECTED: LOAN AMOUNT (₹) | H8: SELECTED: TXN VALUE (₹) | K8: SELECTED: REPAY RATE
N9: This selector only highlights one branch's numbers in the KPI cards below. The 4 comparison charts always show all 5 branches side by side, since that's the point of a branch comparison.
B10: All-Branch Comparison Charts
N13: =HYPERLINK("#Home!A1","← Back to Home") -> ← Back to Home

Sheet RawData_Customers
A1: CustomerID | B1: CustomerName | C1: Gender | D1: Age | E1: City | F1: Branch | G1: Occupation | H1: MonthlyIncome | I1: AccountType | J1: AccountBalance | K1: CustomerSince
A2: C0001 | B2: Forum Rana | C2: Female | D2: 55 | E2: Kanpur | F2: Kanpur Civil Lines Branch | G2: Salaried | H2: 40500 | I2: Savings | J2: 200900 | K2: 2023-01-04
A3: C0002 | B3: Balhaar Wason | C3: Male | D3: 38 | E3: Agra | F3: Agra Sadar Branch | G3: Self-Employed | H3: 99200 | I3: Salary | J3: 9600 | K3: 2019-05-30
A4: C0003 | B4: Qadim Bhardwaj | C4: Male | D4: 36 | E4: Lucknow | F4: Lucknow City Branch | G4: Self-Employed | H4: 19900 | I4: Savings | J4: 29400 | K4: 2018-01-07
A5: C0004 | B5: Anjali Chadha | C5: Female | D5: 31 | E5: Lucknow | F5: Lucknow City Branch | G5: Government Employee | H5: 67500 | I5: Savings | J5: 6000 | K5: 2019-07-04
A6: C0005 | B6: Shaurya Boase | C6: Male | D6: 42 | E6: Meerut | F6: Meerut Cantt Branch | G6: Self-Employed | H6: 43800 | I6: Savings | J6: 13700 | K6: 2019-06-25
A7: C0006 | B7: Chakradev Samra | C7: Male | D7: 45 | E7: Meerut | F7: Meerut Cantt Branch | G7: Government Employee | H7: 46700 | I7: Savings | J7: 1500 | K7: 2018-08-14
A8: C0007 | B8: David Kapoor | C8: Male | D8: 43 | E8: Meerut | F8: Meerut Cantt Branch | G8: Salaried | H8: 50000 | I8: Salary | J8: 17000 | K8: 2019-01-11
A9: C0008 | B9: Rushil Bawa | C9: Male | D9: 46 | E9: Meerut | F9: Meerut Cantt Branch | G9: Self-Employed | H9: 49700 | I9: Savings | J9: 9200 | K9: 2018-02-04
A10: C0009 | B10: Arin Deol | C10: Male | D10: 55 | E10: Meerut | F10: Meerut Cantt Branch | G10: Salaried | H10: 50500 | I10: Savings | J10: 72600 | K10: 2024-08-18
A11: C0010 | B11: Ubika Dhawan | C11: Female | D11: 21 | E11: Agra | F11: Agra Sadar Branch | G11: Self-Employed | H11: 45500 | I11: Salary | J11: 39900 | K11: 2021-01-21
A12: C0011 | B12: Nikita Golla | C12: Female | D12: 32 | E12: Kanpur | F12: Kanpur Civil Lines Branch | G12: Government Employee | H12: 11400 | I12: Current | J12: 6800 | K12: 2019-09-27
A13: C0012 | B13: Girindra Pradhan | C13: Male | D13: 42 | E13: Meerut | F13: Meerut Cantt Branch | G13: Salaried | H13: 57600 | I13: Savings | J13: 28200 | K13: 2020-11-07
... A401: C0400 | B401: Abdul Bhalla | C401: Male | D401: 27 | E401: Lucknow | F401: Lucknow City Branch | G401: Retired | H401: 31200 | I401: Current | J401: 49200 | K401: 2021-05-30

Sheet RawData_Loans
A1: LoanID | B1: CustomerID | C1: Branch | D1: LoanType | E1: LoanAmount | F1: InterestRate | G1: TenureMonths | H1: EMIAmount | I1: StartDate | J1: MonthsElapsed | K1: EMIsPaid | L1: EMIsMissed | M1: LoanStatus | N1: OutstandingAmount
A2: L0001 | B2: C0266 | C2: Kanpur Civil Lines Branch | D2: Personal Loan | E2: 512000 | F2: 11.57 | G2: 30 | H2: 19735 | I2: 2020-10-16 | J2: 30 | K2: 28 | L2: 2 | M2: Active | N2: 208081
A3: L0002 | B3: C0066 | C3: Agra Sadar Branch | D3: Home Loan | E3: 3874000 | F3: 8.93 | G3: 144 | H3: 43935 | I3: 2021-03-10 | J3: 66 | K3: 63 | L3: 3 | M3: Overdue | N3: 2351652
A4: L0003 | B4: C0121 | C4: Noida Sector 18 Branch | D4: Auto Loan | E4: 485000 | F4: 10.89 | G4: 66 | H4: 9800 | I4: 2021-01-10 | J4: 66 | K4: 62 | L4: 4 | M4: Overdue | N4: 150820
A5: L0004 | B5: C0133 | C5: Kanpur Civil Lines Branch | D5: Personal Loan | E5: 566000 | F5: 11.47 | G5: 24 | H5: 26504 | I5: 2019-03-14 | J5: 24 | K5: 21 | L5: 3 | M5: Overdue | N5: 259879
A6: L0005 | B6: C0379 | C6: Lucknow City Branch | D6: Business Loan | E6: 1911000 | F6: 15.81 | G6: 66 | H6: 43524 | I6: 2024-11-22 | J6: 22 | K6: 20 | L6: 2 | M6: Active | N6: 1432236
A7: L0006 | B7: C0027 | C7: Lucknow City Branch | D7: Auto Loan | E7: 1015000 | F7: 8.83 | G7: 48 | H7: 25176 | I7: 2021-04-02 | J7: 48 | K7: 46 | L7: 2 | M7: Active | N7: 378047
A8: L0007 | B8: C0288 | C8: Kanpur Civil Lines Branch | D8: Auto Loan | E8: 578000 | F8: 9.91 | G8: 66 | H8: 11395 | I8: 2024-05-11 | J8: 28 | K8: 27 | L8: 1 | M8: Active | N8: 408784
A9: L0008 | B9: C0112 | C9: Meerut Cantt Branch | D9: Personal Loan | E9: 254000 | F9: 12.54 | G9: 30 | H9: 9907 | I9: 2022-10-12 | J9: 30 | K9: 26 | L9: 4 | M9: Overdue | N9: 112330
A10: L0009 | B10: C0281 | C10: Noida Sector 18 Branch | D10: Auto Loan | E10: 251000 | F10: 8.52 | G10: 48 | H10: 6189 | I10: 2024-11-24 | J10: 22 | K10: 21 | L10: 1 | M10: Active | N10: 179517
A11: L0010 | B11: C0165 | C11: Noida Sector 18 Branch | D11: Home Loan | E11: 1780000 | F11: 8.14 | G11: 108 | H11: 23303 | I11: 2025-05-02 | J11: 16 | K11: 14 | L11: 2 | M11: Active | N11: 1600567
A12: L0011 | B12: C0057 | C12: Agra Sadar Branch | D12: Business Loan | E12: 1531000 | F12: 15.78 | G12: 42 | H12: 47674 | I12: 2024-08-13 | J12: 25 | K12: 24 | L12: 1 | M12: Active | N12: 901703
A13: L0012 | B13: C0275 | C13: Noida Sector 18 Branch | D13: Auto Loan | E13: 244000 | F13: 9.37 | G13: 60 | H13: 5109 | I13: 2021-05-01 | J13: 60 | K13: 56 | L13: 4 | M13: Overdue | N13: 86643
... A321: L0320 | B321: C0111 | C321: Lucknow City Branch | D321: Personal Loan | E321: 97000 | F321: 13.51 | G321: 12 | H321: 8687 | I321: 2025-02-16 | J321: 12 | K321: 10 | L321: 2 | M321: Active | N321: 49221

Sheet RawData_Transactions
A1: TransactionID | B1: CustomerID | C1: Branch | D1: TransactionDate | E1: TransactionType | F1: Amount
A2: T00001 | B2: C0001 | C2: Kanpur Civil Lines Branch | D2: 2025-09-23 | E2: Withdrawal | F2: 19151
A3: T00002 | B3: C0001 | C3: Kanpur Civil Lines Branch | D3: 2025-09-29 | E3: Withdrawal | F3: 2591
A4: T00003 | B4: C0001 | C4: Kanpur Civil Lines Branch | D4: 2025-09-28 | E4: Bill Payment | F4: 20352
A5: T00004 | B5: C0001 | C5: Kanpur Civil Lines Branch | D5: 2026-08-31 | E5: Fund Transfer | F5: 14390
A6: T00005 | B6: C0001 | C6: Kanpur Civil Lines Branch | D6: 2026-02-27 | E6: Fund Transfer | F6: 20263
A7: T00006 | B7: C0001 | C7: Kanpur Civil Lines Branch | D7: 2026-03-01 | E7: Fund Transfer | F7: 12281
A8: T00007 | B8: C0002 | C8: Agra Sadar Branch | D8: 2026-06-28 | E8: EMI Payment | F8: 34743
A9: T00008 | B9: C0002 | C9: Agra Sadar Branch | D9: 2026-07-22 | E9: Fund Transfer | F9: 1229
A10: T00009 | B10: C0002 | C10: Agra Sadar Branch | D10: 2026-05-15 | E10: Fund Transfer | F10: 42739
A11: T00010 | B11: C0002 | C11: Agra Sadar Branch | D11: 2026-01-10 | E11: Withdrawal | F11: 21007
A12: T00011 | B12: C0002 | C12: Agra Sadar Branch | D12: 2026-02-01 | E12: Withdrawal | F12: 29035
A13: T00012 | B13: C0002 | C13: Agra Sadar Branch | D13: 2025-12-30 | E13: Fund Transfer | F13: 17007
... A3607: T03606 | B3607: C0400 | C3607: Lucknow City Branch | D3607: 2025-10-21 | E3607: Deposit | F3607: 15631

Sheet Lists
A1: BranchFilterList | B1: BranchHighlightList
A2: All Branches | B2: Agra Sadar Branch
A3: Agra Sadar Branch | B3: Kanpur Civil Lines Branch
A4: Kanpur Civil Lines Branch | B4: Lucknow City Branch
A5: Lucknow City Branch | B5: Meerut Cantt Branch
A6: Meerut Cantt Branch | B6: Noida Sector 18 Branch
A7: Noida Sector 18 Branch

Sheet Calc
A2: HOME - KPI
A3: Total Customers (filtered) | B3: =SUMPRODUCT((CustTbl[Branch]=IF(Home!$N$4="All Branches",CustTbl[Branch],Home!$N$4))*1) -> 400
A4: Total Loan Amount (filtered) | B4: =SUMPRODUCT((LoanTbl[Branch]=IF(Home!$N$4="All Branches",LoanTbl[Branch],Home!$N$4))*LoanTbl[LoanAmount]) -> 359793000
A5: Total Transactions (filtered) | B5: =SUMPRODUCT((TxnTbl[Branch]=IF(Home!$N$4="All Branches",TxnTbl[Branch],Home!$N$4))*1) -> 3606
A6: Avg Repayment Rate % (filtered) | B6: =IFERROR(SUMPRODUCT((LoanTbl[Branch]=IF(Home!$N$4="All Branches",LoanTbl[Branch],Home!$N$4))*LoanTbl[EMIsPaid])/SUMPRODUCT((LoanTbl[Branch]=IF(Home!$N$4="All Branches",LoanTbl[Branch],Home!$N$4))*LoanTbl[MonthsElapsed])*100,0) -> 93.743195
D8: Top Branch (unfiltered, by loan amount)
A9: HOME - Customers by Branch (unfiltered) | E9: =INDEX(Calc!$A$10:$A$14,MATCH(MAX(Calc!$C$10:$C$14),Calc!$C$10:$C$14,0)) -> Noida Sector 18 Branch
A10: Agra Sadar Branch | B10: =SUMPRODUCT((CustTbl[Branch]="Agra Sadar Branch")*1) -> 77 | C10: =SUMPRODUCT((LoanTbl[Branch]="Agra Sadar Branch")*LoanTbl[LoanAmount]) -> 63121000
A11: Kanpur Civil Lines Branch | B11: =SUMPRODUCT((CustTbl[Branch]="Kanpur Civil Lines Branch")*1) -> 68 | C11: =SUMPRODUCT((LoanTbl[Branch]="Kanpur Civil Lines Branch")*LoanTbl[LoanAmount]) -> 63320000
A12: Lucknow City Branch | B12: =SUMPRODUCT((CustTbl[Branch]="Lucknow City Branch")*1) -> 80 | C12: =SUMPRODUCT((LoanTbl[Branch]="Lucknow City Branch")*LoanTbl[LoanAmount]) -> 65514000
A13: Meerut Cantt Branch | B13: =SUMPRODUCT((CustTbl[Branch]="Meerut Cantt Branch")*1) -> 74 | C13: =SUMPRODUCT((LoanTbl[Branch]="Meerut Cantt Branch")*LoanTbl[LoanAmount]) -> 66478000
A14: Noida Sector 18 Branch | B14: =SUMPRODUCT((CustTbl[Branch]="Noida Sector 18 Branch")*1) -> 101 | C14: =SUMPRODUCT((LoanTbl[Branch]="Noida Sector 18 Branch")*LoanTbl[LoanAmount]) -> 101360000
A17: HOME - Loan Mix by Type (unfiltered)
A18: Auto Loan | B18: =SUMPRODUCT((LoanTbl[LoanType]="Auto Loan")*1) -> 83
A19: Business Loan | B19: =SUMPRODUCT((LoanTbl[LoanType]="Business Loan")*1) -> 85
A20: Home Loan | B20: =SUMPRODUCT((LoanTbl[LoanType]="Home Loan")*1) -> 71
A21: Personal Loan | B21: =SUMPRODUCT((LoanTbl[LoanType]="Personal Loan")*1) -> 81
A30: CUSTOMER - KPI
A31: Total Customers | B31: =SUMPRODUCT((CustTbl[Branch]=IF(Customer!$N$4="All Branches",CustTbl[Branch],Customer!$N$4))*1) -> 77
A32: Avg Age | B32: =IFERROR(SUMPRODUCT((CustTbl[Branch]=IF(Customer!$N$4="All Branches",CustTbl[Branch],Customer!$N$4))*CustTbl[Age])/SUMPRODUCT((CustTbl[Branch]=IF(Customer!$N$4="All Branches",CustTbl[Branch],Customer!$N$4))*1),0) -> 36.363636
A33: Avg Monthly Income | B33: =IFERROR(SUMPRODUCT((CustTbl[Branch]=IF(Customer!$N$4="All Branches",CustTbl[Branch],Customer!$N$4))*CustTbl[MonthlyIncome])/SUMPRODUCT((CustTbl[Branch]=IF(Customer!$N$4="All Branches",CustTbl[Branch],Customer!$N$4))*1),0) -> 50632.468
A36: CUSTOMER - Age Distribution
A37: 21-30 | B37: =SUMPRODUCT((CustTbl[Branch]=IF(Customer!$N$4="All Branches",CustTbl[Branch],Customer!$N$4))*(CustTbl[Age]>=21)*(CustTbl[Age]<=30)*1) -> 22
A38: 31-40 | B38: =SUMPRODUCT((CustTbl[Branch]=IF(Customer!$N$4="All Branches",CustTbl[Branch],Customer!$N$4))*(CustTbl[Age]>=31)*(CustTbl[Age]<=40)*1) -> 27
A39: 41-50 | B39: =SUMPRODUCT((CustTbl[Branch]=IF(Customer!$N$4="All Branches",CustTbl[Branch],Customer!$N$4))*(CustTbl[Age]>=41)*(CustTbl[Age]<=50)*1) -> 24
A40: 51-60 | B40: =SUMPRODUCT((CustTbl[Branch]=IF(Customer!$N$4="All Branches",CustTbl[Branch],Customer!$N$4))*(CustTbl[Age]>=51)*(CustTbl[Age]<=60)*1) -> 3
A41: 61-70 | B41: =SUMPRODUCT((CustTbl[Branch]=IF(Customer!$N$4="All Branches",CustTbl[Branch],Customer!$N$4))*(CustTbl[Age]>=61)*(CustTbl[Age]<=70)*1) -> 1
A44: CUSTOMER - Gender Split
A45: Male | B45: =SUMPRODUCT((CustTbl[Branch]=IF(Customer!$N$4="All Branches",CustTbl[Branch],Customer!$N$4))*(CustTbl[Gender]="Male")*1) -> 44
A46: Female | B46: =SUMPRODUCT((CustTbl[Branch]=IF(Customer!$N$4="All Branches",CustTbl[Branch],Customer!$N$4))*(CustTbl[Gender]="Female")*1) -> 33
A49: CUSTOMER - Occupation Breakdown
A50: Business Owner | B50: =SUMPRODUCT((CustTbl[Branch]=IF(Customer!$N$4="All Branches",CustTbl[Branch],Customer!$N$4))*(CustTbl[Occupation]="Business Owner")*1) -> 14
A51: Government Employee | B51: =SUMPRODUCT((CustTbl[Branch]=IF(Customer!$N$4="All Branches",CustTbl[Branch],Customer!$N$4))*(CustTbl[Occupation]="Government Employee")*1) -> 15
A52: Retired | B52: =SUMPRODUCT((CustTbl[Branch]=IF(Customer!$N$4="All Branches",CustTbl[Branch],Customer!$N$4))*(CustTbl[Occupation]="Retired")*1) -> 7
A53: Salaried | B53: =SUMPRODUCT((CustTbl[Branch]=IF(Customer!$N$4="All Branches",CustTbl[Branch],Customer!$N$4))*(CustTbl[Occupation]="Salaried")*1) -> 23
A54: Self-Employed | B54: =SUMPRODUCT((CustTbl[Branch]=IF(Customer!$N$4="All Branches",CustTbl[Branch],Customer!$N$4))*(CustTbl[Occupation]="Self-Employed")*1) -> 18
A57: CUSTOMER - Income Segment
A58: Low (<25k) | B58: =SUMPRODUCT((CustTbl[Branch]=IF(Customer!$N$4="All Branches",CustTbl[Branch],Customer!$N$4))*(CustTbl[MonthlyIncome]>=0)*(CustTbl[MonthlyIncome]<25000)*1) -> 8
A59: Mid (25k-50k) | B59: =SUMPRODUCT((CustTbl[Branch]=IF(Customer!$N$4="All Branches",CustTbl[Branch],Customer!$N$4))*(CustTbl[MonthlyIncome]>=25000)*(CustTbl[MonthlyIncome]<50000)*1) -> 39
A60: High (50k-1L) | B60: =SUMPRODUCT((CustTbl[Branch]=IF(Customer!$N$4="All Branches",CustTbl[Branch],Customer!$N$4))*(CustTbl[MonthlyIncome]>=50000)*(CustTbl[MonthlyIncome]<100000)*1) -> 23
A61: Premium (>1L) | B61: =SUMPRODUCT((CustTbl[Branch]=IF(Customer!$N$4="All Branches",CustTbl[Branch],Customer!$N$4))*(CustTbl[MonthlyIncome]>=100000)*(CustTbl[MonthlyIncome]<1000000000)*1) -> 7
A75: TRANSACTION - KPI
A76: Total Transactions | B76: =SUMPRODUCT((TxnTbl[Branch]=IF(Transaction!$N$4="All Branches",TxnTbl[Branch],Transaction!$N$4))*1) -> 605
A77: Total Value | B77: =SUMPRODUCT((TxnTbl[Branch]=IF(Transaction!$N$4="All Branches",TxnTbl[Branch],Transaction!$N$4))*TxnTbl[Amount]) -> 11670458
A78: Avg Value | B78: =IFERROR(SUMPRODUCT((TxnTbl[Branch]=IF(Transaction!$N$4="All Branches",TxnTbl[Branch],Transaction!$N$4))*TxnTbl[Amount])/SUMPRODUCT((TxnTbl[Branch]=IF(Transaction!$N$4="All Branches",TxnTbl[Branch],Transaction!$N$4))*1),0) -> 19290.013
A81: TRANSACTION - Monthly Trend
A82: 2025-09 | B82: =SUMPRODUCT((TxnTbl[Branch]=IF(Transaction!$N$4="All Branches",TxnTbl[Branch],Transaction!$N$4))*(TEXT(TxnTbl[TransactionDate],"YYYY-MM")="2025-09")*1) -> 49
A83: 2025-10 | B83: =SUMPRODUCT((TxnTbl[Branch]=IF(Transaction!$N$4="All Branches",TxnTbl[Branch],Transaction!$N$4))*(TEXT(TxnTbl[TransactionDate],"YYYY-MM")="2025-10")*1) -> 49
A84: 2025-11 | B84: =SUMPRODUCT((TxnTbl[Branch]=IF(Transaction!$N$4="All Branches",TxnTbl[Branch],Transaction!$N$4))*(TEXT(TxnTbl[TransactionDate],"YYYY-MM")="2025-11")*1) -> 48
A85: 2025-12 | B85: =SUMPRODUCT((TxnTbl[Branch]=IF(Transaction!$N$4="All Branches",TxnTbl[Branch],Transaction!$N$4))*(TEXT(TxnTbl[TransactionDate],"YYYY-MM")="2025-12")*1) -> 48
A86: 2026-01 | B86: =SUMPRODUCT((TxnTbl[Branch]=IF(Transaction!$N$4="All Branches",TxnTbl[Branch],Transaction!$N$4))*(TEXT(TxnTbl[TransactionDate],"YYYY-MM")="2026-01")*1) -> 48
A87: 2026-02 | B87: =SUMPRODUCT((TxnTbl[Branch]=IF(Transaction!$N$4="All Branches",TxnTbl[Branch],Transaction!$N$4))*(TEXT(TxnTbl[TransactionDate],"YYYY-MM")="2026-02")*1) -> 33
A88: 2026-03 | B88: =SUMPRODUCT((TxnTbl[Branch]=IF(Transaction!$N$4="All Branches",TxnTbl[Branch],Transaction!$N$4))*(TEXT(TxnTbl[TransactionDate],"YYYY-MM")="2026-03")*1) -> 53
A89: 2026-04 | B89: =SUMPRODUCT((TxnTbl[Branch]=IF(Transaction!$N$4="All Branches",TxnTbl[Branch],Transaction!$N$4))*(TEXT(TxnTbl[TransactionDate],"YYYY-MM")="2026-04")*1) -> 56
A90: 2026-05 | B90: =SUMPRODUCT((TxnTbl[Branch]=IF(Transaction!$N$4="All Branches",TxnTbl[Branch],Transaction!$N$4))*(TEXT(TxnTbl[TransactionDate],"YYYY-MM")="2026-05")*1) -> 58
A91: 2026-06 | B91: =SUMPRODUCT((TxnTbl[Branch]=IF(Transaction!$N$4="All Branches",TxnTbl[Branch],Transaction!$N$4))*(TEXT(TxnTbl[TransactionDate],"YYYY-MM")="2026-06")*1) -> 68
A92: 2026-07 | B92: =SUMPRODUCT((TxnTbl[Branch]=IF(Transaction!$N$4="All Branches",TxnTbl[Branch],Transaction!$N$4))*(TEXT(TxnTbl[TransactionDate],"YYYY-MM")="2026-07")*1) -> 56
A93: 2026-08 | B93: =SUMPRODUCT((TxnTbl[Branch]=IF(Transaction!$N$4="All Branches",TxnTbl[Branch],Transaction!$N$4))*(TEXT(TxnTbl[TransactionDate],"YYYY-MM")="2026-08")*1) -> 37
A96: TRANSACTION - Type Breakdown (count)
A97: Bill Payment | B97: =SUMPRODUCT((TxnTbl[Branch]=IF(Transaction!$N$4="All Branches",TxnTbl[Branch],Transaction!$N$4))*(TxnTbl[TransactionType]="Bill Payment")*1) -> 87 | C97: =IFERROR(SUMPRODUCT((TxnTbl[Branch]=IF(Transaction!$N$4="All Branches",TxnTbl[Branch],Transaction!$N$4))*(TxnTbl[TransactionType]="Bill Payment")*TxnTbl[Amount])/SUMPRODUCT((TxnTbl[Branch]=IF(Transaction!$N$4="All Branches",TxnTbl[Branch],Transaction!$N$4))*(TxnTbl[TransactionType]="Bill Payment")*1),0) -> 16464.46
A98: Deposit | B98: =SUMPRODUCT((TxnTbl[Branch]=IF(Transaction!$N$4="All Branches",TxnTbl[Branch],Transaction!$N$4))*(TxnTbl[TransactionType]="Deposit")*1) -> 157 | C98: =IFERROR(SUMPRODUCT((TxnTbl[Branch]=IF(Transaction!$N$4="All Branches",TxnTbl[Branch],Transaction!$N$4))*(TxnTbl[TransactionType]="Deposit")*TxnTbl[Amount])/SUMPRODUCT((TxnTbl[Branch]=IF(Transaction!$N$4="All Branches",TxnTbl[Branch],Transaction!$N$4))*(TxnTbl[TransactionType]="Deposit")*1),0) -> 28475.911
A99: EMI Payment | B99: =SUMPRODUCT((TxnTbl[Branch]=IF(Transaction!$N$4="All Branches",TxnTbl[Branch],Transaction!$N$4))*(TxnTbl[TransactionType]="EMI Payment")*1) -> 76 | C99: =IFERROR(SUMPRODUCT((TxnTbl[Branch]=IF(Transaction!$N$4="All Branches",TxnTbl[Branch],Transaction!$N$4))*(TxnTbl[TransactionType]="EMI Payment")*TxnTbl[Amount])/SUMPRODUCT((TxnTbl[Branch]=IF(Transaction!$N$4="All Branches",TxnTbl[Branch],Transaction!$N$4))*(TxnTbl[TransactionType]="EMI Payment")*1),0) -> 18888.579
A100: Fund Transfer | B100: =SUMPRODUCT((TxnTbl[Branch]=IF(Transaction!$N$4="All Branches",TxnTbl[Branch],Transaction!$N$4))*(TxnTbl[TransactionType]="Fund Transfer")*1) -> 164 | C100: =IFERROR(SUMPRODUCT((TxnTbl[Branch]=IF(Transaction!$N$4="All Branches",TxnTbl[Branch],Transaction!$N$4))*(TxnTbl[TransactionType]="Fund Transfer")*TxnTbl[Amount])/SUMPRODUCT((TxnTbl[Branch]=IF(Transaction!$N$4="All Branches",TxnTbl[Branch],Transaction!$N$4))*(TxnTbl[TransactionType]="Fund Transfer")*1),0) -> 15247.28
A101: Withdrawal | B101: =SUMPRODUCT((TxnTbl[Branch]=IF(Transaction!$N$4="All Branches",TxnTbl[Branch],Transaction!$N$4))*(TxnTbl[TransactionType]="Withdrawal")*1) -> 121 | C101: =IFERROR(SUMPRODUCT((TxnTbl[Branch]=IF(Transaction!$N$4="All Branches",TxnTbl[Branch],Transaction!$N$4))*(TxnTbl[TransactionType]="Withdrawal")*TxnTbl[Amount])/SUMPRODUCT((TxnTbl[Branch]=IF(Transaction!$N$4="All Branches",TxnTbl[Branch],Transaction!$N$4))*(TxnTbl[TransactionType]="Withdrawal")*1),0) -> 15134.264
A135: LOAN - KPI
A136: Total Loans | B136: =SUMPRODUCT((LoanTbl[Branch]=IF(LoanPortfolio!$N$4="All Branches",LoanTbl[Branch],LoanPortfolio!$N$4))*1) -> 320
A137: Total Loan Amount | B137: =SUMPRODUCT((LoanTbl[Branch]=IF(LoanPortfolio!$N$4="All Branches",LoanTbl[Branch],LoanPortfolio!$N$4))*LoanTbl[LoanAmount]) -> 359793000
A138: Avg Loan Amount | B138: =IFERROR(SUMPRODUCT((LoanTbl[Branch]=IF(LoanPortfolio!$N$4="All Branches",LoanTbl[Branch],LoanPortfolio!$N$4))*LoanTbl[LoanAmount])/SUMPRODUCT((LoanTbl[Branch]=IF(LoanPortfolio!$N$4="All Branches",LoanTbl[Branch],LoanPortfolio!$N$4))*1),0) -> 1124353.1
A139: Avg Interest Rate | B139: =IFERROR(SUMPRODUCT((LoanTbl[Branch]=IF(LoanPortfolio!$N$4="All Branches",LoanTbl[Branch],LoanPortfolio!$N$4))*LoanTbl[InterestRate])/SUMPRODUCT((LoanTbl[Branch]=IF(LoanPortfolio!$N$4="All Branches",LoanTbl[Branch],LoanPortfolio!$N$4))*1),0) -> 11.249
A142: LOAN - By Type (amount, count, rate)
A143: Auto Loan | B143: =SUMPRODUCT((LoanTbl[Branch]=IF(LoanPortfolio!$N$4="All Branches",LoanTbl[Branch],LoanPortfolio!$N$4))*(LoanTbl[LoanType]="Auto Loan")*LoanTbl[LoanAmount]) -> 51634000 | C143: =SUMPRODUCT((LoanTbl[Branch]=IF(LoanPortfolio!$N$4="All Branches",LoanTbl[Branch],LoanPortfolio!$N$4))*(LoanTbl[LoanType]="Auto Loan")*1) -> 83 | D143: =IFERROR(SUMPRODUCT((LoanTbl[Branch]=IF(LoanPortfolio!$N$4="All Branches",LoanTbl[Branch],LoanPortfolio!$N$4))*(LoanTbl[LoanType]="Auto Loan")*LoanTbl[InterestRate])/SUMPRODUCT((LoanTbl[Branch]=IF(LoanPortfolio!$N$4="All Branches",LoanTbl[Branch],LoanPortfolio!$N$4))*(LoanTbl[LoanType]="Auto Loan")*1),0) -> 9.7379518
A144: Business Loan | B144: =SUMPRODUCT((LoanTbl[Branch]=IF(LoanPortfolio!$N$4="All Branches",LoanTbl[Branch],LoanPortfolio!$N$4))*(LoanTbl[LoanType]="Business Loan")*LoanTbl[LoanAmount]) -> 113794000 | C144: =SUMPRODUCT((LoanTbl[Branch]=IF(LoanPortfolio!$N$4="All Branches",LoanTbl[Branch],LoanPortfolio!$N$4))*(LoanTbl[LoanType]="Business Loan")*1) -> 85 | D144: =IFERROR(SUMPRODUCT((LoanTbl[Branch]=IF(LoanPortfolio!$N$4="All Branches",LoanTbl[Branch],LoanPortfolio!$N$4))*(LoanTbl[LoanType]="Business Loan")*LoanTbl[InterestRate])/SUMPRODUCT((LoanTbl[Branch]=IF(LoanPortfolio!$N$4="All Branches",LoanTbl[Branch],LoanPortfolio!$N$4))*(LoanTbl[LoanType]="Business Loan")*1),0) -> 13.560706
A145: Home Loan | B145: =SUMPRODUCT((LoanTbl[Branch]=IF(LoanPortfolio!$N$4="All Branches",LoanTbl[Branch],LoanPortfolio!$N$4))*(LoanTbl[LoanType]="Home Loan")*LoanTbl[LoanAmount]) -> 166540000 | C145: =SUMPRODUCT((LoanTbl[Branch]=IF(LoanPortfolio!$N$4="All Branches",LoanTbl[Branch],LoanPortfolio!$N$4))*(LoanTbl[LoanType]="Home Loan")*1) -> 71 | D145: =IFERROR(SUMPRODUCT((LoanTbl[Branch]=IF(LoanPortfolio!$N$4="All Branches",LoanTbl[Branch],LoanPortfolio!$N$4))*(LoanTbl[LoanType]="Home Loan")*LoanTbl[InterestRate])/SUMPRODUCT((LoanTbl[Branch]=IF(LoanPortfolio!$N$4="All Branches",LoanTbl[Branch],LoanPortfolio!$N$4))*(LoanTbl[LoanType]="Home Loan")*1),0) -> 8.2230986
A146: Personal Loan | B146: =SUMPRODUCT((LoanTbl[Branch]=IF(LoanPortfolio!$N$4="All Branches",LoanTbl[Branch],LoanPortfolio!$N$4))*(LoanTbl[LoanType]="Personal Loan")*LoanTbl[LoanAmount]) -> 27825000 | C146: =SUMPRODUCT((LoanTbl[Branch]=IF(LoanPortfolio!$N$4="All Branches",LoanTbl[Branch],LoanPortfolio!$N$4))*(LoanTbl[LoanType]="Personal Loan")*1) -> 81 | D146: =IFERROR(SUMPRODUCT((LoanTbl[Branch]=IF(LoanPortfolio!$N$4="All Branches",LoanTbl[Branch],LoanPortfolio!$N$4))*(LoanTbl[LoanType]="Personal Loan")*LoanTbl[InterestRate])/SUMPRODUCT((LoanTbl[Branch]=IF(LoanPortfolio!$N$4="All Branches",LoanTbl[Branch],LoanPortfolio!$N$4))*(LoanTbl[LoanType]="Personal Loan")*1),0) -> 13.023827
A149: LOAN - Status Breakdown
A150: Active | B150: =SUMPRODUCT((LoanTbl[Branch]=IF(LoanPortfolio!$N$4="All Branches",LoanTbl[Branch],LoanPortfolio!$N$4))*(LoanTbl[LoanStatus]="Active")*1) -> 140
A151: Closed | B151: =SUMPRODUCT((LoanTbl[Branch]=IF(LoanPortfolio!$N$4="All Branches",LoanTbl[Branch],LoanPortfolio!$N$4))*(LoanTbl[LoanStatus]="Closed")*1) -> 69
A152: Overdue | B152: =SUMPRODUCT((LoanTbl[Branch]=IF(LoanPortfolio!$N$4="All Branches",LoanTbl[Branch],LoanPortfolio!$N$4))*(LoanTbl[LoanStatus]="Overdue")*1) -> 111
A158: EMI - KPI
A159: Avg Repayment Rate % | B159: =IFERROR(SUMPRODUCT((LoanTbl[Branch]=IF(EMI_Repayment!$N$4="All Branches",LoanTbl[Branch],EMI_Repayment!$N$4))*LoanTbl[EMIsPaid])/SUMPRODUCT((LoanTbl[Branch]=IF(EMI_Repayment!$N$4="All Branches",LoanTbl[Branch],EMI_Repayment!$N$4))*LoanTbl[MonthsElapsed])*100,0) -> 93.965132
A160: Loans Overdue (3+ missed) | B160: =SUMPRODUCT((LoanTbl[Branch]=IF(EMI_Repayment!$N$4="All Branches",LoanTbl[Branch],EMI_Repayment!$N$4))*(LoanTbl[EMIsMissed]>=3)*1) -> 18
A161: Total EMI Collected (est.) | B161: =SUMPRODUCT((LoanTbl[Branch]=IF(EMI_Repayment!$N$4="All Branches",LoanTbl[Branch],EMI_Repayment!$N$4))*LoanTbl[EMIsPaid]*LoanTbl[EMIAmount]) -> 52291274
A162: On-time Loans % (0 missed) | B162: =IFERROR(SUMPRODUCT((LoanTbl[Branch]=IF(EMI_Repayment!$N$4="All Branches",LoanTbl[Branch],EMI_Repayment!$N$4))*(LoanTbl[EMIsMissed]=0)*1)/SUMPRODUCT((LoanTbl[Branch]=IF(EMI_Repayment!$N$4="All Branches",LoanTbl[Branch],EMI_Repayment!$N$4))*1)*100,0) -> 12.903226
A165: EMI - Avg EMI & Repayment Rate by Type
A166: Auto Loan | B166: =IFERROR(SUMPRODUCT((LoanTbl[Branch]=IF(EMI_Repayment!$N$4="All Branches",LoanTbl[Branch],EMI_Repayment!$N$4))*(LoanTbl[LoanType]="Auto Loan")*LoanTbl[EMIAmount])/SUMPRODUCT((LoanTbl[Branch]=IF(EMI_Repayment!$N$4="All Branches",LoanTbl[Branch],EMI_Repayment!$N$4))*(LoanTbl[LoanType]="Auto Loan")*1),0) -> 24484.789 | C166: =IFERROR(SUMPRODUCT((LoanTbl[Branch]=IF(EMI_Repayment!$N$4="All Branches",LoanTbl[Branch],EMI_Repayment!$N$4))*(LoanTbl[LoanType]="Auto Loan")*LoanTbl[EMIsPaid])/SUMPRODUCT((LoanTbl[Branch]=IF(EMI_Repayment!$N$4="All Branches",LoanTbl[Branch],EMI_Repayment!$N$4))*(LoanTbl[LoanType]="Auto Loan")*LoanTbl[MonthsElapsed])*100,0) -> 95.163585
A167: Business Loan | B167: =IFERROR(SUMPRODUCT((LoanTbl[Branch]=IF(EMI_Repayment!$N$4="All Branches",LoanTbl[Branch],EMI_Repayment!$N$4))*(LoanTbl[LoanType]="Business Loan")*LoanTbl[EMIAmount])/SUMPRODUCT((LoanTbl[Branch]=IF(EMI_Repayment!$N$4="All Branches",LoanTbl[Branch],EMI_Repayment!$N$4))*(LoanTbl[LoanType]="Business Loan")*1),0) -> 42462.231 | C167: =IFERROR(SUMPRODUCT((LoanTbl[Branch]=IF(EMI_Repayment!$N$4="All Branches",LoanTbl[Branch],EMI_Repayment!$N$4))*(LoanTbl[LoanType]="Business Loan")*LoanTbl[EMIsPaid])/SUMPRODUCT((LoanTbl[Branch]=IF(EMI_Repayment!$N$4="All Branches",LoanTbl[Branch],EMI_Repayment!$N$4))*(LoanTbl[LoanType]="Business Loan")*LoanTbl[MonthsElapsed])*100,0) -> 93.6
A168: Home Loan | B168: =IFERROR(SUMPRODUCT((LoanTbl[Branch]=IF(EMI_Repayment!$N$4="All Branches",LoanTbl[Branch],EMI_Repayment!$N$4))*(LoanTbl[LoanType]="Home Loan")*LoanTbl[EMIAmount])/SUMPRODUCT((LoanTbl[Branch]=IF(EMI_Repayment!$N$4="All Branches",LoanTbl[Branch],EMI_Repayment!$N$4))*(LoanTbl[LoanType]="Home Loan")*1),0) -> 30090.846 | C168: =IFERROR(SUMPRODUCT((LoanTbl[Branch]=IF(EMI_Repayment!$N$4="All Branches",LoanTbl[Branch],EMI_Repayment!$N$4))*(LoanTbl[LoanType]="Home Loan")*LoanTbl[EMIsPaid])/SUMPRODUCT((LoanTbl[Branch]=IF(EMI_Repayment!$N$4="All Branches",LoanTbl[Branch],EMI_Repayment!$N$4))*(LoanTbl[LoanType]="Home Loan")*LoanTbl[MonthsElapsed])*100,0) -> 93.741851
A169: Personal Loan | B169: =IFERROR(SUMPRODUCT((LoanTbl[Branch]=IF(EMI_Repayment!$N$4="All Branches",LoanTbl[Branch],EMI_Repayment!$N$4))*(LoanTbl[LoanType]="Personal Loan")*LoanTbl[EMIAmount])/SUMPRODUCT((LoanTbl[Branch]=IF(EMI_Repayment!$N$4="All Branches",LoanTbl[Branch],EMI_Repayment!$N$4))*(LoanTbl[LoanType]="Personal Loan")*1),0) -> 19159.529 | C169: =IFERROR(SUMPRODUCT((LoanTbl[Branch]=IF(EMI_Repayment!$N$4="All Branches",LoanTbl[Branch],EMI_Repayment!$N$4))*(LoanTbl[LoanType]="Personal Loan")*LoanTbl[EMIsPaid])/SUMPRODUCT((LoanTbl[Branch]=IF(EMI_Repayment!$N$4="All Branches",LoanTbl[Branch],EMI_Repayment!$N$4))*(LoanTbl[LoanType]="Personal Loan")*LoanTbl[MonthsElapsed])*100,0) -> 92.602041
A172: EMI - Missed EMI Distribution
A173: 0 Missed | B173: =SUMPRODUCT((LoanTbl[Branch]=IF(EMI_Repayment!$N$4="All Branches",LoanTbl[Branch],EMI_Repayment!$N$4))*(LoanTbl[EMIsMissed]=0)*1) -> 8
A174: 1 Missed | B174: =SUMPRODUCT((LoanTbl[Branch]=IF(EMI_Repayment!$N$4="All Branches",LoanTbl[Branch],EMI_Repayment!$N$4))*(LoanTbl[EMIsMissed]=1)*1) -> 23
A175: 2 Missed | B175: =SUMPRODUCT((LoanTbl[Branch]=IF(EMI_Repayment!$N$4="All Branches",LoanTbl[Branch],EMI_Repayment!$N$4))*(LoanTbl[EMIsMissed]=2)*1) -> 13
A176: 3+ Missed | B176: =SUMPRODUCT((LoanTbl[Branch]=IF(EMI_Repayment!$N$4="All Branches",LoanTbl[Branch],EMI_Repayment!$N$4))*(LoanTbl[EMIsMissed]>=3)*1) -> 18
A178: EMI - Paid vs Missed (sum)
A179: EMIs Paid | B179: =SUMPRODUCT((LoanTbl[Branch]=IF(EMI_Repayment!$N$4="All Branches",LoanTbl[Branch],EMI_Repayment!$N$4))*LoanTbl[EMIsPaid]) -> 2102
A180: EMIs Missed | B180: =SUMPRODUCT((LoanTbl[Branch]=IF(EMI_Repayment!$N$4="All Branches",LoanTbl[Branch],EMI_Repayment!$N$4))*LoanTbl[EMIsMissed]) -> 135
A190: BRANCHPERF - per branch (unfiltered, for comparison charts)
A191: Agra Sadar Branch | B191: =SUMPRODUCT((CustTbl[Branch]="Agra Sadar Branch")*1) -> 77 | C191: =SUMPRODUCT((LoanTbl[Branch]="Agra Sadar Branch")*LoanTbl[LoanAmount]) -> 63121000 | D191: =SUMPRODUCT((TxnTbl[Branch]="Agra Sadar Branch")*TxnTbl[Amount]) -> 12531235 | E191: =IFERROR(SUMPRODUCT((LoanTbl[Branch]="Agra Sadar Branch")*LoanTbl[EMIsPaid])/SUMPRODUCT((LoanTbl[Branch]="Agra Sadar Branch")*LoanTbl[MonthsElapsed])*100,0) -> 93.3391
A192: Kanpur Civil Lines Branch | B192: =SUMPRODUCT((CustTbl[Branch]="Kanpur Civil Lines Branch")*1) -> 68 | C192: =SUMPRODUCT((LoanTbl[Branch]="Kanpur Civil Lines Branch")*LoanTbl[LoanAmount]) -> 63320000 | D192: =SUMPRODUCT((TxnTbl[Branch]="Kanpur Civil Lines Branch")*TxnTbl[Amount]) -> 11670458 | E192: =IFERROR(SUMPRODUCT((LoanTbl[Branch]="Kanpur Civil Lines Branch")*LoanTbl[EMIsPaid])/SUMPRODUCT((LoanTbl[Branch]="Kanpur Civil Lines Branch")*LoanTbl[MonthsElapsed])*100,0) -> 94.516854
A193: Lucknow City Branch | B193: =SUMPRODUCT((CustTbl[Branch]="Lucknow City Branch")*1) -> 80 | C193: =SUMPRODUCT((LoanTbl[Branch]="Lucknow City Branch")*LoanTbl[LoanAmount]) -> 65514000 | D193: =SUMPRODUCT((TxnTbl[Branch]="Lucknow City Branch")*TxnTbl[Amount]) -> 13254293 | E193: =IFERROR(SUMPRODUCT((LoanTbl[Branch]="Lucknow City Branch")*LoanTbl[EMIsPaid])/SUMPRODUCT((LoanTbl[Branch]="Lucknow City Branch")*LoanTbl[MonthsElapsed])*100,0) -> 91.790687
...
